wds_files_CoursePythonAdult_1/__init__.py
wds_files_CoursePythonAdult_1/sprite_types_cpa1/battle_city_items/base.ini
wds_files_CoursePythonAdult_1/sprite_types_cpa1/battle_city_items/base.png
wds_files_CoursePythonAdult_1/sprite_types_cpa1/battle_city_items/base_defend_brick.ini
wds_files_CoursePythonAdult_1/sprite_types_cpa1/battle_city_items/base_defend_brick.png
wds_files_CoursePythonAdult_1/sprite_types_cpa1/battle_city_items/base_defend_steel.ini
wds_files_CoursePythonAdult_1/sprite_types_cpa1/battle_city_items/base_defend_steel.png
wds_files_CoursePythonAdult_1/sprite_types_cpa1/battle_city_items/base_grave.ini
wds_files_CoursePythonAdult_1/sprite_types_cpa1/battle_city_items/base_grave.png
wds_files_CoursePythonAdult_1/sprite_types_cpa1/battle_city_items/block_brick.ini
wds_files_CoursePythonAdult_1/sprite_types_cpa1/battle_city_items/block_brick.png
wds_files_CoursePythonAdult_1/sprite_types_cpa1/battle_city_items/block_brick_half.ini
wds_files_CoursePythonAdult_1/sprite_types_cpa1/battle_city_items/block_brick_half.png
wds_files_CoursePythonAdult_1/sprite_types_cpa1/battle_city_items/block_brushes.ini
wds_files_CoursePythonAdult_1/sprite_types_cpa1/battle_city_items/block_bushes.png
wds_files_CoursePythonAdult_1/sprite_types_cpa1/battle_city_items/block_gift_bomb.ini
wds_files_CoursePythonAdult_1/sprite_types_cpa1/battle_city_items/block_gift_bomb.png
wds_files_CoursePythonAdult_1/sprite_types_cpa1/battle_city_items/block_gift_gun.ini
wds_files_CoursePythonAdult_1/sprite_types_cpa1/battle_city_items/block_gift_gun.png
wds_files_CoursePythonAdult_1/sprite_types_cpa1/battle_city_items/block_gift_helmet.ini
wds_files_CoursePythonAdult_1/sprite_types_cpa1/battle_city_items/block_gift_helmet.png
wds_files_CoursePythonAdult_1/sprite_types_cpa1/battle_city_items/block_gift_shovel.ini
wds_files_CoursePythonAdult_1/sprite_types_cpa1/battle_city_items/block_gift_shovel.png
wds_files_CoursePythonAdult_1/sprite_types_cpa1/battle_city_items/block_gift_star.ini
wds_files_CoursePythonAdult_1-0.1.3.1.dist-info/METADATA
wds_files_CoursePythonAdult_1-0.1.3.1.dist-info/WHEEL
wds_files_CoursePythonAdult_1-0.1.3.1.dist-info/top_level.txt
wds_files_CoursePythonAdult_1-0.1.3.1.dist-info/RECORD
