Metadata-Version: 2.1
Name: wds-files-CoursePythonAdult-1
Version: 0.1.3.1
Summary: UNKNOWN
Home-page: UNKNOWN
Author: UNKNOWN
Author-email: UNKNOWN
License: UNKNOWN
Platform: UNKNOWN
Requires-Dist: wrap-data-source (==0.1.*,>=0.1.0)
